apitester_lite/__init__.py
apitester_lite/cli.py
apitester_lite/core.py
apitester_lite-0.4.0.dist-info/licenses/LICENSE
apitester_lite-0.4.0.dist-info/METADATA
apitester_lite-0.4.0.dist-info/WHEEL
apitester_lite-0.4.0.dist-info/entry_points.txt
apitester_lite-0.4.0.dist-info/top_level.txt
apitester_lite-0.4.0.dist-info/RECORD
