Metadata-Version: 2.4
Name: apitester-lite
Version: 0.4.0
Summary: Lightweight API testing CLI
Home-page: https://github.com/Shrinidhi064/apitester-lite
Author: Shrinidhi
Classifier: Programming Language :: Python :: 3
Classifier: License :: OSI Approved :: MIT License
License-File: LICENSE
Requires-Dist: requests
Dynamic: author
Dynamic: classifier
Dynamic: description
Dynamic: description-content-type
Dynamic: home-page
Dynamic: license-file
Dynamic: requires-dist
Dynamic: summary
